restgdf/__init__.py
restgdf/directory/__init__.py
restgdf/directory/directory.py
restgdf/featurelayer/__init__.py
restgdf/featurelayer/featurelayer.py
restgdf/utils/__init__.py
restgdf/utils/crawl.py
restgdf/utils/getgdf.py
restgdf/utils/getinfo.py
restgdf/utils/utils.py
restgdf-1.0.0.dist-info/LICENSE
restgdf-1.0.0.dist-info/METADATA
restgdf-1.0.0.dist-info/WHEEL
restgdf-1.0.0.dist-info/top_level.txt
restgdf-1.0.0.dist-info/RECORD
