Metadata-Version: 2.1
Name: restgdf
Version: 1.0.0
Summary: improved esri rest io for geopandas
Author: Joshua Sundance Bailey
License: MIT License
Project-URL: Homepage, https://github.com/joshuasundance-swca/restgdf
Keywords: geopandas,esri,arcgis
Classifier: License :: OSI Approved :: MIT License
Classifier: Operating System :: OS Independent
Classifier: Programming Language :: Python
Classifier: Programming Language :: Python :: 3
Classifier: Programming Language :: Python :: 3.9
Requires-Python: >=3.9
License-File: LICENSE
Requires-Dist: aiohttp
Requires-Dist: geopandas
Requires-Dist: pandas
Requires-Dist: pyogrio
Requires-Dist: requests
Provides-Extra: dev
Requires-Dist: bumpver ; extra == 'dev'
Requires-Dist: coverage ; extra == 'dev'
Requires-Dist: coverage-badge ; extra == 'dev'
Requires-Dist: pre-commit ; extra == 'dev'
Requires-Dist: pytest ; extra == 'dev'
Requires-Dist: pytest-asyncio ; extra == 'dev'
Provides-Extra: doc
Requires-Dist: sphinx ; extra == 'doc'
Requires-Dist: sphinx-rtd-theme ; extra == 'doc'
